{
  "Natural Sciences": [
    "Mathematics",
    "Computer and information sciences",
    "Physical sciences",
    "Chemical sciences",
    "Earth and related environmental sciences",
    "Biological sciences",
    "Other natural sciences"
  ],
  "Engineering and Technology": [
    "Civil engineering",
    "Electrical engineering, electronic engineering, information engineering",
    "Mechanical engineering",
    "Chemical engineering",
    "Materials engineering",
    "Medical engineering",
    "Environmental engineering",
    "Environmental biotechnology",
    "Industrial biotechnology",
    "Nano-technology",
    "Other engineering and technologies"
  ],
  "Medical and Health Sciences": [
    "Basic medicine",
    "Clinical medicine",
    "Health sciences",
    "Health biotechnology",
    "Other medical sciences"
  ],
  "Agricultural Sciences": [
    "Agriculture, forestry, and fisheries",
    "Animal and diary science",
    "Veterinary science",
    "Agricultural biotechnology",
    "Other agricultural sciences"
  ],
  "Social Sciences": [
    "Psychology",
    "Economics and business",
    "Educational sciences",
    "Sociology",
    "Law",
    "Political science",
    "Social and economic geography",
    "Media and communications",
    "Other social sciences"
  ],
  "Humanities": [
    "History and archeology",
    "Language and literature",
    "Philosophy, ethics and religion",
    "Art (arts, history of arts, performing arts, music)",
    "Other humanities"
  ]
}
